Metadata-Version: 2.1
Name: panelctmc
Version: 0.1.1
Summary: Continuous Time Markov Chain for daily panel data and annual transition probabilities
Home-page: http://github.com/kmedian/panelctmc
Author: Ulf Hamster
Author-email: 554c46@gmail.com
License: MIT
Platform: UNKNOWN
Requires-Python: >=3.6
